yta_video_opengl/__init__.py
yta_video_opengl/abstract.py
yta_video_opengl/blender/__init__.py
yta_video_opengl/blender/cpu.py
yta_video_opengl/blender/gpu.py
yta_video_opengl/blender/utils.py
yta_video_opengl/context.py
yta_video_opengl/effects.py
yta_video_opengl/new_nodes/__init__.py
yta_video_opengl/nodes/__init__.py
yta_video_opengl/nodes/audio/__init__.py
yta_video_opengl/nodes/audio/abstract.py
yta_video_opengl/nodes/audio/experimental.py
yta_video_opengl/nodes/cpu.py
yta_video_opengl/nodes/gpu.py
yta_video_opengl/nodes/timed.py
yta_video_opengl/nodes/video/__init__.py
yta_video_opengl/nodes/video/cpu.py
yta_video_opengl/nodes/video/experimental.py
yta_video_opengl/nodes/video/gpu.py
yta_video_opengl/nodes/video/transitions/__init__.py
yta_video_opengl/nodes/video/transitions/cpu.py
yta_video_opengl/nodes/video/transitions/gpu.py
yta_video_opengl/selection_mask.py
yta_video_opengl/texture/__init__.py
yta_video_opengl/texture/handler.py
yta_video_opengl/uniforms/__init__.py
yta_video_opengl/uniforms/enum.py
yta_video_opengl/utils.py
yta_video_opengl-0.2.1.dist-info/licenses/LICENSE
yta_video_opengl-0.2.1.dist-info/METADATA
yta_video_opengl-0.2.1.dist-info/WHEEL
yta_video_opengl-0.2.1.dist-info/RECORD
