Metadata-Version: 2.4
Name: yta-video-opengl
Version: 0.2.1
Summary: Youtube Autonomous Video OpenGL Module
License-File: LICENSE
Author: danialcala94
Author-email: danielalcalavalera@gmail.com
Requires-Python: ==3.9
Classifier: Programming Language :: Python :: 3
Classifier: Programming Language :: Python :: 3.9
Requires-Dist: moderngl (>=0.0.1,<9.0.0)
Requires-Dist: numpy (>=0.0.1,<9.0.0)
Requires-Dist: yta_programming (>=0.0.1,<1.0.0)
Requires-Dist: yta_validation (>=0.0.1,<1.0.0)
